<?xml version="1.0" encoding="utf-8" ?>
<Sentences>
    <Sentence id="0" value="How Are You?" />
    <Sentence id="0" value="Absolutely not." />
    <Sentence id="0" value="Are you coming with me?" />
    <Sentence id="0" value="Are you sure?" />
    <Sentence id="0" value="we almost there?" />
    <Sentence id="0" value="As soon as possible." />
    <Sentence id="0" value="Believe me." />
    <Sentence id="0" value="Buy it!" />
    <Sentence id="0" value="Call me tomorrow." />
    <Sentence id="0" value="Can you speak slowly?" />
    <Sentence id="0" value="Come with me." />
    <Sentence id="0" value="Congratulations." />
    <Sentence id="0" value="Do it right!" />
    <Sentence id="0" value="Do you mean it?" />
    <Sentence id="0" value="Do you see him often?" />
    <Sentence id="0" value="Do you understand?" />
    <Sentence id="0" value="Do you want it?" />
    <Sentence id="0" value="Do you want something?" />
    <Sentence id="0" value="Don’t do it." />
    <Sentence id="0" value="Don’t exaggerate." />
    <Sentence id="0" value="Don’t tell me that." />
    <Sentence id="0" value="Give me a hand." />
    <Sentence id="0" value="Go right ahead." />
    <Sentence id="0" value="Have a good trip." />
    <Sentence id="0" value="Have a nice day." />
    <Sentence id="0" value="Have another one." />
    <Sentence id="0" value="Have you finished?" />
    <Sentence id="0" value="He doesn’t have time." />
    <Sentence id="0" value="He is on his way." />
    <Sentence id="0" value="How are you doing?" />
    <Sentence id="0" value="How long are you staying?" />
    <Sentence id="0" value="How much?" />
    <Sentence id="0" value="I am crazy about her." />
    <Sentence id="0" value="I am wasting my time." />
    <Sentence id="0" value="I can do it." />
    <Sentence id="0" value="I can’t believe it." />
    <Sentence id="0" value="I can’t wait." />
    <Sentence id="0" value="I don’t have time." />
    <Sentence id="0" value="I don’t know anybody." />
    <Sentence id="0" value="I don’t like it." />
    <Sentence id="0" value="I don’t think so." />
    <Sentence id="0" value="I feel much better." />
    <Sentence id="0" value="I found it." />
    <Sentence id="0" value="I hate you!" />
    <Sentence id="0" value="I hope so." />
    <Sentence id="0" value="I knew it." />
    <Sentence id="0" value="I love you." />
    <Sentence id="0" value="I noticed that." />
    <Sentence id="0" value="I see." />
    <Sentence id="0" value="I think so." />
    <Sentence id="0" value="I want to speak with him." />
    <Sentence id="0" value="I won." />
    <Sentence id="0" value="I would like a cup of coffee, please." />
    <Sentence id="0" value="I’m hungry." />
    <Sentence id="0" value="I’m leaving." />
    <Sentence id="0" value="I’m sorry." />
    <Sentence id="0" value="I’m used to it." />
    <Sentence id="0" value="I’ll miss you." />
    <Sentence id="0" value="I’ll try." />
    <Sentence id="0" value="I’m bored." />
    <Sentence id="0" value="I’m busy." />
    <Sentence id="0" value="I’m having fun." />
    <Sentence id="0" value="I’m ready." />
    <Sentence id="0" value="I’ve got it." />
    <Sentence id="0" value="It’s incredible!" />
    <Sentence id="0" value="Is it far?" />
    <Sentence id="0" value="It doesn’t matter." />
    <Sentence id="0" value="It smells good." />
    <Sentence id="0" value="It’s about time." />
    <Sentence id="0" value="It’s all right." />
    <Sentence id="0" value="It’s easy." />
    <Sentence id="0" value="It’s good." />
    <Sentence id="0" value="It’s near here." />
    <Sentence id="0" value="It’s nothing." />
    <Sentence id="0" value="It’s time to go." />
    <Sentence id="0" value="It’s different." />
    <Sentence id="0" value="It’s funny." />
    <Sentence id="0" value="It’s impossible." />
    <Sentence id="0" value="It’s not bad." />
    <Sentence id="0" value="It’s not difficult." />
    <Sentence id="0" value="It’s not worth it." />
    <Sentence id="0" value="It’s obvious." />
    <Sentence id="0" value="It’s the same thing." />
    <Sentence id="0" value="It’s your turn." />
    <Sentence id="0" value="Me too." />
    <Sentence id="0" value="Not yet." />
    <Sentence id="0" value="Relax!" />
    <Sentence id="0" value="See you tomorrow." />
    <Sentence id="0" value="She is my best friend." />
    <Sentence id="0" value="She is so smart." />
    <Sentence id="0" value="Slow down!" />
    <Sentence id="0" value="Tell me." />
    <Sentence id="0" value="Thank you very much." />
    <Sentence id="0" value="That happens." />
    <Sentence id="0" value="That’s enough." />
    <Sentence id="0" value="That’s interesting." />
    <Sentence id="0" value="That’s right." />
    <Sentence id="0" value="That’s true." />
    <Sentence id="0" value="There are too many people here." />
    <Sentence id="0" value="They like each other." />
    <Sentence id="0" value="Think about it." />
    <Sentence id="0" value="Too bad!" />
    <Sentence id="0" value="Wait for me." />
    <Sentence id="0" value="What did you say?" />
    <Sentence id="0" value="What do you think?" />
    <Sentence id="0" value="What is he talking about?" />
    <Sentence id="0" value="What terrible weather!" />
    <Sentence id="0" value="Where are you going?" />
    <Sentence id="0" value="What’s the date today?" />
    <Sentence id="0" value="Where is he?" />
    <Sentence id="0" value="You are impatient." />
    <Sentence id="0" value="You look tired." />
    <Sentence id="0" value="You surprise me." />
    <Sentence id="0" value="You’re crazy." />
    <Sentence id="0" value="You’re welcome." />
    <Sentence id="0" value="You’re always right." />
    <Sentence id="0" value="You’re in a bad mood." />
    <Sentence id="0" value="You’re lying." />
    <Sentence id="0" value="You’re wrong." />
</Sentences>